array_algorithms/__init__.py
array_algorithms/array_algorithms.py
feature_processing/__init__.py
feature_processing/pandas_based.py
feature_stuff/__init__.py
feature_stuff/categorical.py
feature_stuff/numeric.py
feature_stuff/pandas_based.py
feature_stuff/partial_dependence.py
feature_stuff/text.py
feature_stuff/time_series.py
feature_stuff-0.0.dev6.dist-info/LICENSE.txt
feature_stuff-0.0.dev6.dist-info/METADATA
feature_stuff-0.0.dev6.dist-info/RECORD
feature_stuff-0.0.dev6.dist-info/WHEEL
feature_stuff-0.0.dev6.dist-info/top_level.txt
graph_search_algorithms/__init__.py
graph_search_algorithms/graph_search_algorithms.py
model_features_insights_extractions/__init__.py
model_features_insights_extractions/boosted_trees_features_insights.py
