Metadata-Version: 2.1
Name: feature-stuff
Version: 0.0.dev6
Summary: Feature extraction, processing and interpretation algorithms and functions for machine learning and data science.
Home-page: https://github.com/hiflyin/Advanced-Feature-Stuff-Lib
Author: Mihaela Mares
Author-email: mihaela.andreea.mares@gmail.com
License: UNKNOWN
Keywords: machine_learning data_science AI ML feature_extraction
Platform: UNKNOWN
Classifier: Development Status :: 4 - Beta
Classifier: Intended Audience :: Developers
Classifier: Topic :: Scientific/Engineering :: Artificial Intelligence
Classifier: License :: OSI Approved :: MIT License
Classifier: Programming Language :: Python :: 2
Classifier: Programming Language :: Python :: 2.7
Classifier: Programming Language :: Python :: 3
Classifier: Programming Language :: Python :: 3.4
Classifier: Programming Language :: Python :: 3.5
Classifier: Programming Language :: Python :: 3.6
Provides-Extra: test
Provides-Extra: dev
Requires-Dist: pandas (>=0.19.2)
Requires-Dist: numpy (>=1.12.1)
Requires-Dist: scikit-learn (>=0.18)
Requires-Dist: scipy (>=0.19.0)
Requires-Dist: xgboost (>=0.6)
Provides-Extra: dev
Requires-Dist: check-manifest; extra == 'dev'
Provides-Extra: test
Requires-Dist: coverage; extra == 'test'
